nwae/math/Cluster.py
nwae/math/Constants.py
nwae/math/NumpyUtil.py
nwae/math/NwaeMathUnitTest.py
nwae/math/Obfuscate.py
nwae/math/config/Config.py
nwae/math/data/Grouping.py
nwae/math/data/Rank.py
nwae/math/fit/markov/HiddenMarkov.py
nwae/math/measures/CenterOfMass.py
nwae/math/nn/loss/CategoricalCrossEntropy.py
nwae/math/number/e.py
nwae/math/number/pi.py
nwae/math/optimization/Eidf.py
nwae/math/suggest/SuggestDataProfile.py
nwae/math/suggest/SuggestMetric.py
nwae/math/suggest/SuggestUnitTest.py
nwae/math/tree/MultiTree.py
nwae/math/tree/MultiTreeNode.py
nwae.math-0.2.5.dist-info/METADATA
nwae.math-0.2.5.dist-info/WHEEL
nwae.math-0.2.5.dist-info/top_level.txt
nwae.math-0.2.5.dist-info/RECORD
