Metadata-Version: 2.1
Name: nwae.math
Version: 0.2.5
Summary: ML
Home-page: UNKNOWN
Author: nwae
Author-email: mapktah@ya.ru
License: UNKNOWN
Platform: UNKNOWN
Requires-Dist: numpy
Requires-Dist: pandas
Requires-Dist: scipy
